esxi_utils/__init__.py
esxi_utils/client.py
esxi_utils/datastore.py
esxi_utils/file/__init__.py
esxi_utils/file/ovf.py
esxi_utils/file/xml.py
esxi_utils/firewall/__init__.py
esxi_utils/firewall/firewall.py
esxi_utils/firewall/rule.py
esxi_utils/firewall/ruleset.py
esxi_utils/networking/__init__.py
esxi_utils/networking/distributedportgroup.py
esxi_utils/networking/distributedvswitch.py
esxi_utils/networking/physicalnic.py
esxi_utils/networking/portgroup.py
esxi_utils/networking/vmkernelnic.py
esxi_utils/networking/vswitch.py
esxi_utils/util/__init__.py
esxi_utils/util/decorators.py
esxi_utils/util/exceptions.py
esxi_utils/util/log.py
esxi_utils/util/parse.py
esxi_utils/util/response.py
esxi_utils/util/usbkeycodes.py
esxi_utils/util/connect/__init__.py
esxi_utils/util/connect/cisco.py
esxi_utils/util/connect/esxi.py
esxi_utils/util/connect/panos.py
esxi_utils/util/connect/ssh.py
esxi_utils/util/connect/unix.py
esxi_utils/util/connect/winrm.py
esxi_utils/util/connect/textfsm_templates/show_logging_trap_info.textfsm
esxi_utils/util/connect/textfsm_templates/show_run_flow_exporter.textfsm
esxi_utils/vm/__init__.py
esxi_utils/vm/screencapture.py
esxi_utils/vm/snapshot.py
esxi_utils/vm/usb.py
esxi_utils/vm/virtualmachine.py
esxi_utils/vm/vnc.py
esxi_utils/vm/hardware/__init__.py
esxi_utils/vm/hardware/cdrom.py
esxi_utils/vm/hardware/device.py
esxi_utils/vm/hardware/disk.py
esxi_utils/vm/hardware/floppy.py
esxi_utils/vm/hardware/nic.py
esxi_utils/vm/hardware/video_card.py
esxi_utils/vm/tools/__init__.py
esxi_utils/vm/tools/guesttools.py
esxi_utils/vm/tools/panos.py
esxi_utils/vm/tools/unix.py
esxi_utils/vm/tools/windows.py
esxi_utils/vm/types/__init__.py
esxi_utils/vm/types/cisco.py
esxi_utils/vm/types/linux.py
esxi_utils/vm/types/ostype.py
esxi_utils/vm/types/panos.py
esxi_utils/vm/types/windows.py
esxi_utils-3.22.0.dist-info/licenses/LICENSE
esxi_utils-3.22.0.dist-info/METADATA
esxi_utils-3.22.0.dist-info/WHEEL
esxi_utils-3.22.0.dist-info/top_level.txt
esxi_utils-3.22.0.dist-info/RECORD
